[{"id":"a4a8ed7c.bbe0b","type":"tab","label":"OPENDATA","disabled":false,"info":""},{"id":"f6487e9d.7a408","type":"inject","z":"a4a8ed7c.bbe0b","name":"","props":[{"p":"payload"},{"p":"topic","vt":"str"}],"repeat":"86400","crontab":"","once":false,"onceDelay":"25","topic":"","payload":"","payloadType":"date","x":150,"y":100,"wires":[["67ec02a5.86793c","a1cec825.28ddc8","ee508609.0b1b38"]]},{"id":"67ec02a5.86793c","type":"http request","z":"a4a8ed7c.bbe0b","name":"","method":"GET","ret":"txt","paytoqs":"ignore","url":"http://opendata.gijon.es/descargar.php?id=1&tipo=JSON","tls":"","persist":false,"proxy":"","authType":"","x":380,"y":100,"wires":[["2d4df9a9.622566"]]},{"id":"9ee63e1e.e52f9","type":"debug","z":"a4a8ed7c.bbe0b","name":"","active":false,"tosidebar":true,"console":false,"tostatus":false,"complete":"false","statusVal":"","statusType":"auto","x":1050,"y":100,"wires":[]},{"id":"2d4df9a9.622566","type":"json","z":"a4a8ed7c.bbe0b","name":"VALORES","property":"payload","action":"","pretty":false,"x":560,"y":100,"wires":[["9ee63e1e.e52f9"]]},{"id":"a1cec825.28ddc8","type":"http request","z":"a4a8ed7c.bbe0b","name":"","method":"GET","ret":"txt","paytoqs":"ignore","url":"http://opendata.gijon.es/descargar.php?id=4&tipo=JSON","tls":"","persist":false,"proxy":"","authType":"","x":380,"y":140,"wires":[["b3aa787e.9e74b8"]]},{"id":"b3aa787e.9e74b8","type":"json","z":"a4a8ed7c.bbe0b","name":"ESTACIONES","property":"payload","action":"","pretty":false,"x":570,"y":140,"wires":[["59863e98.6b896"]]},{"id":"59863e98.6b896","type":"debug","z":"a4a8ed7c.bbe0b","name":"","active":false,"tosidebar":true,"console":false,"tostatus":false,"complete":"false","statusVal":"","statusType":"auto","x":1050,"y":140,"wires":[]},{"id":"ee508609.0b1b38","type":"http request","z":"a4a8ed7c.bbe0b","name":"","method":"GET","ret":"txt","paytoqs":"ignore","url":"http://opendata.gijon.es/descargar.php?id=5&tipo=JSON","tls":"","persist":false,"proxy":"","authType":"","x":380,"y":180,"wires":[["92f7124a.b0eaf"]]},{"id":"92f7124a.b0eaf","type":"json","z":"a4a8ed7c.bbe0b","name":"PARAMETROS","property":"payload","action":"","pretty":false,"x":570,"y":180,"wires":[["341bee58.e147b2"]]},{"id":"8ae641ec.f8f17","type":"debug","z":"a4a8ed7c.bbe0b","name":"","active":false,"tosidebar":true,"console":false,"tostatus":false,"complete":"false","statusVal":"","statusType":"auto","x":1050,"y":180,"wires":[]},{"id":"341bee58.e147b2","type":"function","z":"a4a8ed7c.bbe0b","name":"","func":"var RS={payload:msg.payload.parametrosestaciones};\nreturn msg;","outputs":1,"noerr":0,"initialize":"","finalize":"","libs":[],"x":740,"y":180,"wires":[["8ae641ec.f8f17"]]},{"id":"c54feab6.425848","type":"comment","z":"a4a8ed7c.bbe0b","name":"OPENDATA GIJON","info":"OPENDATA GIJON","x":160,"y":60,"wires":[]}]